siaf/__init__.py
siaf/algorithms/__init__.py
siaf/algorithms/apso.py
siaf/algorithms/base.py
siaf/algorithms/bbpso.py
siaf/algorithms/lso.py
siaf/algorithms/pso.py
siaf/problems/__init__.py
siaf/problems/cvrp.py
siaf/problems/problem.py
siaf/problems/tsp.py
siaf/problems/x2.py
siaf/utils/__init__.py
siaf/utils/common.py
siaf/utils/data.py
siaf/utils/files.py
siaf/utils/gsd.py
siaf/utils/plot.py
src/__init__.py
src/include.py
src/myopt.py
siaf-0.1.1.dist-info/LICENSE
siaf-0.1.1.dist-info/METADATA
siaf-0.1.1.dist-info/WHEEL
siaf-0.1.1.dist-info/top_level.txt
siaf-0.1.1.dist-info/RECORD
